deepviewcore/__init__.py
deepviewcore/filters/__init__.py
deepviewcore/filters/denoise.py
deepviewcore/filters/skip_dark.py
deepviewcore/filters/threshold.py
deepviewcore/filters/to_gray.py
deepviewcore/filters/top_hat.py
deepviewcore/LICENSE
deepviewcore/process/__init__.py
deepviewcore/process/detect_objects.py
deepviewcore/process/preprocess_frame.py
deepviewcore/process/process_frame.py
deepviewcore/shell.py
deepviewcore/tests/detect_contours.py
deepviewcore/tests/detect_events_testing.py
deepviewcore/tests/skip_dark.py
deepviewcore/tests/test.py
deepviewcore/Video.py
deepviewcore-0.1.8.dist-info/entry_points.txt
deepviewcore-0.1.8.dist-info/WHEEL
deepviewcore-0.1.8.dist-info/METADATA
deepviewcore-0.1.8.dist-info/RECORD
